[
	{
		"flag": "https://flagcdn.com/w320/ki.png",
		"name": "Kiribati",
		"capital": "Tarawa"
	},
	{
		"flag": "https://flagcdn.com/w320/bj.png",
		"name": "Benin",
		"capital": "Porto-Novo"
	},
	{
		"flag": "https://flagcdn.com/w320/lb.png",
		"name": "Lebanon",
		"capital": "Beirut"
	},
	{
		"flag": "https://flagcdn.com/w320/jm.png",
		"name": "Jamaica",
		"capital": "Kingston"
	},
	{
		"flag": "https://flagcdn.com/w320/me.png",
		"name": "Montenegro",
		"capital": "Podgorica"
	},
	{
		"flag": "https://flagcdn.com/w320/km.png",
		"name": "Comoros",
		"capital": "Moroni"
	},
	{
		"flag": "https://flagcdn.com/w320/zw.png",
		"name": "Zimbabwe",
		"capital": "Harare"
	},
	{
		"flag": "https://flagcdn.com/w320/td.png",
		"name": "Chad",
		"capital": "N'Djamena"
	},
	{
		"flag": "https://flagcdn.com/w320/et.png",
		"name": "Ethiopia",
		"capital": "Addis Ababa"
	},
	{
		"flag": "https://flagcdn.com/w320/ad.png",
		"name": "Andorra",
		"capital": "Andorra la Vella"
	},
	{
		"flag": "https://flagcdn.com/w320/ag.png",
		"name": "Antigua and Barbuda",
		"capital": "Saint John's"
	},
	{
		"flag": "https://flagcdn.com/w320/us.png",
		"name": "United States",
		"capital": "Washington, D.C."
	},
	{
		"flag": "https://flagcdn.com/w320/gw.png",
		"name": "Guinea-Bissau",
		"capital": "Bissau"
	},

	{
		"flag": "https://flagcdn.com/w320/ca.png",
		"name": "Canada",
		"capital": "Ottawa"
	},
	{
		"flag": "https://flagcdn.com/w320/ke.png",
		"name": "Kenya",
		"capital": "Nairobi"
	},
	{
		"flag": "https://flagcdn.com/w320/cv.png",
		"name": "Cape Verde",
		"capital": "Praia"
	},
	{
		"flag": "https://flagcdn.com/w320/ge.png",
		"name": "Georgia",
		"capital": "Tbilisi"
	},
	{
		"flag": "https://flagcdn.com/w320/sb.png",
		"name": "Solomon Islands",
		"capital": "Honiara"
	},
	{
		"flag": "https://flagcdn.com/w320/cn.png",
		"name": "China",
		"capital": "Beijing"
	},
	{
		"flag": "https://flagcdn.com/w320/rw.png",
		"name": "Rwanda",
		"capital": "Kigali"
	},
	{
		"flag": "https://flagcdn.com/w320/by.png",
		"name": "Belarus",
		"capital": "Minsk"
	},
	{
		"flag": "https://flagcdn.com/w320/pk.png",
		"name": "Pakistan",
		"capital": "Islamabad"
	},
	{
		"flag": "https://flagcdn.com/w320/tl.png",
		"name": "Timor-Leste",
		"capital": "Dili"
	},
	{
		"flag": "https://flagcdn.com/w320/sv.png",
		"name": "El Salvador",
		"capital": "San Salvador"
	},
	{
		"flag": "https://flagcdn.com/w320/uy.png",
		"name": "Uruguay",
		"capital": "Montevideo"
	},
	{
		"flag": "https://flagcdn.com/w320/at.png",
		"name": "Austria",
		"capital": "Vienna"
	},
	{
		"flag": "https://flagcdn.com/w320/er.png",
		"name": "Eritrea",
		"capital": "Asmara"
	},
	{
		"flag": "https://flagcdn.com/w320/za.png",
		"name": "South Africa",
		"capital": ["Pretoria", "Bloemfontein", "Cape Town"]
	},
	{
		"flag": "https://flagcdn.com/w320/zm.png",
		"name": "Zambia",
		"capital": "Lusaka"
	},
	{
		"flag": "https://flagcdn.com/w320/ne.png",
		"name": "Niger",
		"capital": "Niamey"
	},
	{
		"flag": "https://flagcdn.com/w320/la.png",
		"name": "Laos",
		"capital": "Vientiane"
	},
	{
		"flag": "https://flagcdn.com/w320/cy.png",
		"name": "Cyprus",
		"capital": "Nicosia"
	},
	{
		"flag": "https://flagcdn.com/w320/ec.png",
		"name": "Ecuador",
		"capital": "Quito"
	},
	{
		"flag": "https://flagcdn.com/w320/lr.png",
		"name": "Liberia",
		"capital": "Monrovia"
	},
	{
		"flag": "https://flagcdn.com/w320/ug.png",
		"name": "Uganda",
		"capital": "Kampala"
	},
	{
		"flag": "https://flagcdn.com/w320/gt.png",
		"name": "Guatemala",
		"capital": "Guatemala City"
	},
	{
		"flag": "https://flagcdn.com/w320/mm.png",
		"name": "Myanmar",
		"capital": "Naypyidaw"
	},
	{
		"flag": "https://flagcdn.com/w320/lu.png",
		"name": "Luxembourg",
		"capital": "Luxembourg"
	},
	{
		"flag": "https://flagcdn.com/w320/do.png",
		"name": "Dominican Republic",
		"capital": "Santo Domingo"
	},
	{
		"flag": "https://flagcdn.com/w320/tj.png",
		"name": "Tajikistan",
		"capital": "Dushanbe"
	},
	{
		"flag": "https://flagcdn.com/w320/ml.png",
		"name": "Mali",
		"capital": "Bamako"
	},
	{
		"flag": "https://flagcdn.com/w320/ve.png",
		"name": "Venezuela",
		"capital": "Caracas"
	},
	{
		"flag": "https://flagcdn.com/w320/md.png",
		"name": "Moldova",
		"capital": "Chișinău"
	},
	{
		"flag": "https://flagcdn.com/w320/se.png",
		"name": "Sweden",
		"capital": "Stockholm"
	},
	{
		"flag": "https://flagcdn.com/w320/mv.png",
		"name": "Maldives",
		"capital": "Malé"
	},
	{
		"flag": "https://flagcdn.com/w320/gy.png",
		"name": "Guyana",
		"capital": "Georgetown"
	},
	{
		"flag": "https://flagcdn.com/w320/ph.png",
		"name": "Philippines",
		"capital": "Manila"
	},
	{
		"flag": "https://flagcdn.com/w320/kh.png",
		"name": "Cambodia",
		"capital": "Phnom Penh"
	},
	{
		"flag": "https://flagcdn.com/w320/mn.png",
		"name": "Mongolia",
		"capital": "Ulaanbaatar"
	},
	{
		"flag": "https://flagcdn.com/w320/sy.png",
		"name": "Syria",
		"capital": "Damascus"
	},
	{
		"flag": "https://flagcdn.com/w320/il.png",
		"name": "Israel",
		"capital": "Jerusalem"
	},
	{
		"flag": "https://flagcdn.com/w320/mz.png",
		"name": "Mozambique",
		"capital": "Maputo"
	},
	{
		"flag": "https://flagcdn.com/w320/au.png",
		"name": "Australia",
		"capital": "Canberra"
	},
	{
		"flag": "https://flagcdn.com/w320/am.png",
		"name": "Armenia",
		"capital": "Yerevan"
	},
	{
		"flag": "https://flagcdn.com/w320/ws.png",
		"name": "Samoa",
		"capital": "Apia"
	},
	{
		"flag": "https://flagcdn.com/w320/fj.png",
		"name": "Fiji",
		"capital": "Suva"
	},
	{
		"flag": "https://flagcdn.com/w320/my.png",
		"name": "Malaysia",
		"capital": "Kuala Lumpur"
	},
	{
		"flag": "https://flagcdn.com/w320/to.png",
		"name": "Tonga",
		"capital": "Nuku'alofa"
	},
	{
		"flag": "https://flagcdn.com/w320/fr.png",
		"name": "France",
		"capital": "Paris"
	},
	{
		"flag": "https://flagcdn.com/w320/lc.png",
		"name": "Saint Lucia",
		"capital": "Castries"
	},
	{
		"flag": "https://flagcdn.com/w320/sr.png",
		"name": "Suriname",
		"capital": "Paramaribo"
	},
	{
		"flag": "https://flagcdn.com/w320/bg.png",
		"name": "Bulgaria",
		"capital": "Sofia"
	},
	{
		"flag": "https://flagcdn.com/w320/br.png",
		"name": "Brazil",
		"capital": "Brasília"
	},
	{
		"flag": "https://flagcdn.com/w320/id.png",
		"name": "Indonesia",
		"capital": "Jakarta"
	},
	{
		"flag": "https://flagcdn.com/w320/tv.png",
		"name": "Tuvalu",
		"capital": "Funafuti"
	},
	{
		"flag": "https://flagcdn.com/w320/pw.png",
		"name": "Palau",
		"capital": "Ngerulmud"
	},
	{
		"flag": "https://flagcdn.com/w320/jp.png",
		"name": "Japan",
		"capital": "Tokyo"
	},
	{
		"flag": "https://flagcdn.com/w320/be.png",
		"name": "Belgium",
		"capital": "Brussels"
	},
	{
		"flag": "https://flagcdn.com/w320/es.png",
		"name": "Spain",
		"capital": "Madrid"
	},
	{
		"flag": "https://flagcdn.com/w320/is.png",
		"name": "Iceland",
		"capital": "Reykjavik"
	},
	{
		"flag": "https://flagcdn.com/w320/ie.png",
		"name": "Ireland",
		"capital": "Dublin"
	},
	{
		"flag": "https://flagcdn.com/w320/kg.png",
		"name": "Kyrgyzstan",
		"capital": "Bishkek"
	},
	{
		"flag": "https://flagcdn.com/w320/sz.png",
		"name": "Eswatini",
		"capital": "Mbabane"
	},
	{
		"flag": "https://flagcdn.com/w320/gd.png",
		"name": "Grenada",
		"capital": "St. George's"
	},
	{
		"flag": "https://flagcdn.com/w320/bi.png",
		"name": "Burundi",
		"capital": "Gitega"
	},
	{
		"flag": "https://flagcdn.com/w320/tt.png",
		"name": "Trinidad and Tobago",
		"capital": "Port of Spain"
	},
	{
		"flag": "https://flagcdn.com/w320/jo.png",
		"name": "Jordan",
		"capital": "Amman"
	},
	{
		"flag": "https://flagcdn.com/w320/lt.png",
		"name": "Lithuania",
		"capital": "Vilnius"
	},
	{
		"flag": "https://flagcdn.com/w320/ma.png",
		"name": "Morocco",
		"capital": "Rabat"
	},
	{
		"flag": "https://flagcdn.com/w320/nl.png",
		"name": "Netherlands",
		"capital": "Amsterdam"
	},
	{
		"flag": "https://flagcdn.com/w320/co.png",
		"name": "Colombia",
		"capital": "Bogotá"
	},
	{
		"flag": "https://flagcdn.com/w320/bz.png",
		"name": "Belize",
		"capital": "Belmopan"
	},
	{
		"flag": "https://flagcdn.com/w320/mu.png",
		"name": "Mauritius",
		"capital": "Port Louis"
	},

	{
		"flag": "https://flagcdn.com/w320/bt.png",
		"name": "Bhutan",
		"capital": "Thimphu"
	},
	{
		"flag": "https://flagcdn.com/w320/dj.png",
		"name": "Djibouti",
		"capital": "Djibouti"
	},
	{
		"flag": "https://flagcdn.com/w320/ee.png",
		"name": "Estonia",
		"capital": "Tallinn"
	},
	{
		"flag": "https://flagcdn.com/w320/bf.png",
		"name": "Burkina Faso",
		"capital": "Ouagadougou"
	},
	{
		"flag": "https://flagcdn.com/w320/va.png",
		"name": "Vatican City",
		"capital": "Vatican City"
	},
	{
		"flag": "https://flagcdn.com/w320/gn.png",
		"name": "Guinea",
		"capital": "Conakry"
	},
	{
		"flag": "https://flagcdn.com/w320/ua.png",
		"name": "Ukraine",
		"capital": "Kyiv"
	},
	{
		"flag": "https://flagcdn.com/w320/sm.png",
		"name": "San Marino",
		"capital": "City of San Marino"
	},
	{
		"flag": "https://flagcdn.com/w320/pl.png",
		"name": "Poland",
		"capital": "Warsaw"
	},
	{
		"flag": "https://flagcdn.com/w320/pa.png",
		"name": "Panama",
		"capital": "Panama City"
	},
	{
		"flag": "https://flagcdn.com/w320/cl.png",
		"name": "Chile",
		"capital": "Santiago"
	},
	{
		"flag": "https://flagcdn.com/w320/pt.png",
		"name": "Portugal",
		"capital": "Lisbon"
	},
	{
		"flag": "https://flagcdn.com/w320/bw.png",
		"name": "Botswana",
		"capital": "Gaborone"
	},
	{
		"flag": "https://flagcdn.com/w320/ga.png",
		"name": "Gabon",
		"capital": "Libreville"
	},
	{
		"flag": "https://flagcdn.com/w320/tm.png",
		"name": "Turkmenistan",
		"capital": "Ashgabat"
	},
	{
		"flag": "https://flagcdn.com/w320/it.png",
		"name": "Italy",
		"capital": "Rome"
	},
	{
		"flag": "https://flagcdn.com/w320/mg.png",
		"name": "Madagascar",
		"capital": "Antananarivo"
	},
	{
		"flag": "https://flagcdn.com/w320/cd.png",
		"name": "DR Congo",
		"capital": "Kinshasa"
	},
	{
		"flag": "https://flagcdn.com/w320/vn.png",
		"name": "Vietnam",
		"capital": "Hanoi"
	},
	{
		"flag": "https://flagcdn.com/w320/dm.png",
		"name": "Dominica",
		"capital": "Roseau"
	},
	{
		"flag": "https://flagcdn.com/w320/fm.png",
		"name": "Micronesia",
		"capital": "Palikir"
	},
	{
		"flag": "https://flagcdn.com/w320/tr.png",
		"name": "Turkey",
		"capital": "Ankara"
	},
	{
		"flag": "https://flagcdn.com/w320/kz.png",
		"name": "Kazakhstan",
		"capital": "Nur-Sultan"
	},
	{
		"flag": "https://flagcdn.com/w320/ro.png",
		"name": "Romania",
		"capital": "Bucharest"
	},
	{
		"flag": "https://flagcdn.com/w320/lv.png",
		"name": "Latvia",
		"capital": "Riga"
	},
	{
		"flag": "https://flagcdn.com/w320/tn.png",
		"name": "Tunisia",
		"capital": "Tunis"
	},
	{
		"flag": "https://flagcdn.com/w320/dk.png",
		"name": "Denmark",
		"capital": "Copenhagen"
	},
	{
		"flag": "https://flagcdn.com/w320/hu.png",
		"name": "Hungary",
		"capital": "Budapest"
	},
	{
		"flag": "https://flagcdn.com/w320/uz.png",
		"name": "Uzbekistan",
		"capital": "Tashkent"
	},
	{
		"flag": "https://flagcdn.com/w320/ru.png",
		"name": "Russia",
		"capital": "Moscow"
	},
	{
		"flag": "https://flagcdn.com/w320/gh.png",
		"name": "Ghana",
		"capital": "Accra"
	},
	{
		"flag": "https://flagcdn.com/w320/cg.png",
		"name": "Republic of the Congo",
		"capital": "Brazzaville"
	},
	{
		"flag": "https://flagcdn.com/w320/ao.png",
		"name": "Angola",
		"capital": "Luanda"
	},
	{
		"flag": "https://flagcdn.com/w320/ch.png",
		"name": "Switzerland",
		"capital": "Bern"
	},
	{
		"flag": "https://flagcdn.com/w320/tw.png",
		"name": "Taiwan",
		"capital": "Taipei"
	},
	{
		"flag": "https://flagcdn.com/w320/mk.png",
		"name": "North Macedonia",
		"capital": "Skopje"
	},
	{
		"flag": "https://flagcdn.com/w320/sl.png",
		"name": "Sierra Leone",
		"capital": "Freetown"
	},
	{
		"flag": "https://flagcdn.com/w320/cz.png",
		"name": "Czechia",
		"capital": "Prague"
	},
	{
		"flag": "https://flagcdn.com/w320/pe.png",
		"name": "Peru",
		"capital": "Lima"
	},
	{
		"flag": "https://flagcdn.com/w320/bn.png",
		"name": "Brunei",
		"capital": "Bandar Seri Begawan"
	},
	{
		"flag": "https://flagcdn.com/w320/ye.png",
		"name": "Yemen",
		"capital": "Sana'a"
	},
	{
		"flag": "https://flagcdn.com/w320/hr.png",
		"name": "Croatia",
		"capital": "Zagreb"
	},
	{
		"flag": "https://flagcdn.com/w320/ly.png",
		"name": "Libya",
		"capital": "Tripoli"
	},
	{
		"flag": "https://flagcdn.com/w320/py.png",
		"name": "Paraguay",
		"capital": "Asunción"
	},
	{
		"flag": "https://flagcdn.com/w320/li.png",
		"name": "Liechtenstein",
		"capital": "Vaduz"
	},
	{
		"flag": "https://flagcdn.com/w320/sk.png",
		"name": "Slovakia",
		"capital": "Bratislava"
	},
	{
		"flag": "https://flagcdn.com/w320/eg.png",
		"name": "Egypt",
		"capital": "Cairo"
	},
	{
		"flag": "https://flagcdn.com/w320/lk.png",
		"name": "Sri Lanka",
		"capital": ["Sri Jayawardenepura Kotte", "Colombo"]
	},
	{
		"flag": "https://flagcdn.com/w320/rs.png",
		"name": "Serbia",
		"capital": "Belgrade"
	},
	{
		"flag": "https://flagcdn.com/w320/sn.png",
		"name": "Senegal",
		"capital": "Dakar"
	},
	{
		"flag": "https://flagcdn.com/w320/nz.png",
		"name": "New Zealand",
		"capital": "Wellington"
	},
	{
		"flag": "https://flagcdn.com/w320/kp.png",
		"name": "North Korea",
		"capital": "Pyongyang"
	},
	{
		"flag": "https://flagcdn.com/w320/dz.png",
		"name": "Algeria",
		"capital": "Algiers"
	},
	{
		"flag": "https://flagcdn.com/w320/so.png",
		"name": "Somalia",
		"capital": "Mogadishu"
	},
	{
		"flag": "https://flagcdn.com/w320/sd.png",
		"name": "Sudan",
		"capital": "Khartoum"
	},
	{
		"flag": "https://flagcdn.com/w320/ng.png",
		"name": "Nigeria",
		"capital": "Abuja"
	},
	{
		"flag": "https://flagcdn.com/w320/mh.png",
		"name": "Marshall Islands",
		"capital": "Majuro"
	},
	{
		"flag": "https://flagcdn.com/w320/al.png",
		"name": "Albania",
		"capital": "Tirana"
	},
	{
		"flag": "https://flagcdn.com/w320/bo.png",
		"name": "Bolivia",
		"capital": ["Sucre", "La Paz"]
	},
	{
		"flag": "https://flagcdn.com/w320/pg.png",
		"name": "Papua New Guinea",
		"capital": "Port Moresby"
	},
	{
		"flag": "https://flagcdn.com/w320/qa.png",
		"name": "Qatar",
		"capital": "Doha"
	},
	{
		"flag": "https://flagcdn.com/w320/bb.png",
		"name": "Barbados",
		"capital": "Bridgetown"
	},
	{
		"flag": "https://flagcdn.com/w320/cr.png",
		"name": "Costa Rica",
		"capital": "San José"
	},
	{
		"flag": "https://flagcdn.com/w320/sc.png",
		"name": "Seychelles",
		"capital": "Victoria"
	},
	{
		"flag": "https://flagcdn.com/w320/af.png",
		"name": "Afghanistan",
		"capital": "Kabul"
	},
	{
		"flag": "https://flagcdn.com/w320/nr.png",
		"name": "Nauru",
		"capital": "Yaren"
	},
	{
		"flag": "https://flagcdn.com/w320/gr.png",
		"name": "Greece",
		"capital": "Athens"
	},
	{
		"flag": "https://flagcdn.com/w320/ni.png",
		"name": "Nicaragua",
		"capital": "Managua"
	},
	{
		"flag": "https://flagcdn.com/w320/ae.png",
		"name": "United Arab Emirates",
		"capital": "Abu Dhabi"
	},
	{
		"flag": "https://flagcdn.com/w320/cm.png",
		"name": "Cameroon",
		"capital": "Yaoundé"
	},
	{
		"flag": "https://flagcdn.com/w320/ir.png",
		"name": "Iran",
		"capital": "Tehran"
	},
	{
		"flag": "https://flagcdn.com/w320/mc.png",
		"name": "Monaco",
		"capital": "Monaco"
	},
	{
		"flag": "https://flagcdn.com/w320/ar.png",
		"name": "Argentina",
		"capital": "Buenos Aires"
	},
	{
		"flag": "https://flagcdn.com/w320/mx.png",
		"name": "Mexico",
		"capital": "Mexico City"
	},
	{
		"flag": "https://flagcdn.com/w320/mr.png",
		"name": "Mauritania",
		"capital": "Nouakchott"
	},
	{
		"flag": "https://flagcdn.com/w320/in.png",
		"name": "India",
		"capital": "New Delhi"
	},
	{
		"flag": "https://flagcdn.com/w320/az.png",
		"name": "Azerbaijan",
		"capital": "Baku"
	},
	{
		"flag": "https://flagcdn.com/w320/hn.png",
		"name": "Honduras",
		"capital": "Tegucigalpa"
	},
	{
		"flag": "https://flagcdn.com/w320/tz.png",
		"name": "Tanzania",
		"capital": "Dodoma"
	},
	{
		"flag": "https://flagcdn.com/w320/iq.png",
		"name": "Iraq",
		"capital": "Baghdad"
	},
	{
		"flag": "https://flagcdn.com/w320/bh.png",
		"name": "Bahrain",
		"capital": "Manama"
	},
	{
		"flag": "https://flagcdn.com/w320/kr.png",
		"name": "South Korea",
		"capital": "Seoul"
	},
	{
		"flag": "https://flagcdn.com/w320/gq.png",
		"name": "Equatorial Guinea",
		"capital": "Malabo"
	},
	{
		"flag": "https://flagcdn.com/w320/ls.png",
		"name": "Lesotho",
		"capital": "Maseru"
	},
	{
		"flag": "https://flagcdn.com/w320/np.png",
		"name": "Nepal",
		"capital": "Kathmandu"
	},
	{
		"flag": "https://flagcdn.com/w320/om.png",
		"name": "Oman",
		"capital": "Muscat"
	},
	{
		"flag": "https://flagcdn.com/w320/de.png",
		"name": "Germany",
		"capital": "Berlin"
	},
	{
		"flag": "https://flagcdn.com/w320/ba.png",
		"name": "Bosnia and Herzegovina",
		"capital": "Sarajevo"
	},
	{
		"flag": "https://flagcdn.com/w320/kn.png",
		"name": "Saint Kitts and Nevis",
		"capital": "Basseterre"
	},
	{
		"flag": "https://flagcdn.com/w320/st.png",
		"name": "São Tomé and Príncipe",
		"capital": "São Tomé"
	},
	{
		"flag": "https://flagcdn.com/w320/bs.png",
		"name": "Bahamas",
		"capital": "Nassau"
	},
	{
		"flag": "https://flagcdn.com/w320/no.png",
		"name": "Norway",
		"capital": "Oslo"
	},
	{
		"flag": "https://flagcdn.com/w320/na.png",
		"name": "Namibia",
		"capital": "Windhoek"
	},
	{
		"flag": "https://flagcdn.com/w320/vu.png",
		"name": "Vanuatu",
		"capital": "Port Vila"
	},
	{
		"flag": "https://flagcdn.com/w320/tg.png",
		"name": "Togo",
		"capital": "Lomé"
	},
	{
		"flag": "https://flagcdn.com/w320/sg.png",
		"name": "Singapore",
		"capital": "Singapore"
	},
	{
		"flag": "https://flagcdn.com/w320/bd.png",
		"name": "Bangladesh",
		"capital": "Dhaka"
	},
	{
		"flag": "https://flagcdn.com/w320/gm.png",
		"name": "Gambia",
		"capital": "Banjul"
	},
	{
		"flag": "https://flagcdn.com/w320/si.png",
		"name": "Slovenia",
		"capital": "Ljubljana"
	},
	{
		"flag": "https://flagcdn.com/w320/ci.png",
		"name": "Ivory Coast",
		"capital": "Yamoussoukro"
	},
	{
		"flag": "https://flagcdn.com/w320/cu.png",
		"name": "Cuba",
		"capital": "Havana"
	},
	{
		"flag": "https://flagcdn.com/w320/mt.png",
		"name": "Malta",
		"capital": "Valletta"
	},
	{
		"flag": "https://flagcdn.com/w320/fi.png",
		"name": "Finland",
		"capital": "Helsinki"
	},
	{
		"flag": "https://flagcdn.com/w320/ss.png",
		"name": "South Sudan",
		"capital": "Juba"
	},
	{
		"flag": "https://flagcdn.com/w320/mw.png",
		"name": "Malawi",
		"capital": "Lilongwe"
	},
	{
		"flag": "https://flagcdn.com/w320/ht.png",
		"name": "Haiti",
		"capital": "Port-au-Prince"
	},
	{
		"flag": "https://flagcdn.com/w320/gb.png",
		"name": "United Kingdom",
		"capital": "London"
	},
	{
		"flag": "https://flagcdn.com/w320/sa.png",
		"name": "Saudi Arabia",
		"capital": "Riyadh"
	},
	{
		"flag": "https://flagcdn.com/w320/kw.png",
		"name": "Kuwait",
		"capital": "Kuwait City"
	},
	{
		"flag": "https://flagcdn.com/w320/cf.png",
		"name": "Central African Republic",
		"capital": "Bangui"
	},
	{
		"flag": "https://flagcdn.com/w320/vc.png",
		"name": "Saint Vincent and the Grenadines",
		"capital": "Kingstown"
	},
	{
		"flag": "https://flagcdn.com/w320/th.png",
		"name": "Thailand",
		"capital": "Bangkok"
	}
]
